setup.py
diaolinglib/P_H.py
diaolinglib/__init__.py
diaolinglib/dlai.py
diaolinglib/dmath.py
diaolinglib/draw.py
diaolinglib/pachong.py
diaolinglib.egg-info/PKG-INFO
diaolinglib.egg-info/SOURCES.txt
diaolinglib.egg-info/dependency_links.txt
diaolinglib.egg-info/top_level.txt