Metadata-Version: 1.1
Name: diaolinglib
Version: 0.21.816
Summary: 凋零工作室二代库，拥有数学、画图拓展、生成HTML文件等模块，在一代的基础上更新了不少
Home-page: https://github.com/
Author: Wenxin Chen
Author-email: minecraft_cwx@163.com
License: UNKNOWN
Platform: UNKNOWN
Classifier: Programming Language :: Python :: 3
Classifier: License :: OSI Approved :: MIT License
Classifier: Operating System :: OS Independent
